{
  "Name": "AudioNodeEmitterShape",
  "Namespace": "Windows.Media.Audio",
  "Interfaces": [
    {
      "Name": "IAudioNodeEmitterShape",
      "Namespace": "Windows.Media.Audio",
      "GenericParameters": null,
      "IsArray": false,
      "IsReference": false
    }
  ],
  "Traits": [
    {
      "Interfaces": [
        {
          "Name": "IAudioNodeEmitterShapeStatics",
          "Namespace": "Windows.Media.Audio"
        }
      ],
      "TraitType": "Static"
    },
    {
      "DefaultInterface": {
        "Name": "IAudioNodeEmitterShape",
        "Namespace": "Windows.Media.Audio",
        "GenericParameters": null,
        "IsArray": false,
        "IsReference": false
      },
      "TraitType": "DefaultInterface"
    }
  ],
  "Type": "Class"
}