{
  "Name": "TimedMetadataKind",
  "Namespace": "Windows.Media.Core",
  "Values": {
    "Caption": 0,
    "Chapter": 1,
    "Custom": 2,
    "Data": 3,
    "Description": 4,
    "Subtitle": 5,
    "ImageSubtitle": 6,
    "Speech": 7
  },
  "Traits": [
    {
      "TraitType": "ValueType"
    },
    {
      "Superclass": {
        "Name": "Enum",
        "Namespace": "System",
        "GenericParameters": null,
        "IsArray": false,
        "IsReference": false
      },
      "TraitType": "Superclass"
    }
  ],
  "Type": "Enum"
}