{
  "Name": "PickerConfirmedEventArgs",
  "Namespace": "Windows.UI.Xaml.Controls",
  "Interfaces": [
    {
      "Name": "IPickerConfirmedEventArgs",
      "Namespace": "Windows.UI.Xaml.Controls",
      "GenericParameters": null,
      "IsArray": false,
      "IsReference": false
    }
  ],
  "Traits": [
    {
      "TraitType": "DirectActivation"
    },
    {
      "DefaultInterface": {
        "Name": "IPickerConfirmedEventArgs",
        "Namespace": "Windows.UI.Xaml.Controls",
        "GenericParameters": null,
        "IsArray": false,
        "IsReference": false
      },
      "TraitType": "DefaultInterface"
    },
    {
      "Superclass": {
        "Name": "DependencyObject",
        "Namespace": "Windows.UI.Xaml",
        "GenericParameters": null,
        "IsArray": false,
        "IsReference": false
      },
      "TraitType": "Superclass"
    }
  ],
  "Type": "Class"
}