{
  "Name": "IMediaPlayerRateChangedEventArgs",
  "Namespace": "Windows.Media.Playback",
  "Guid": "40600d583b614bb2989ffc65608b6cab",
  "Methods": [
    {
      "Name": "get_NewRate",
      "Parameters": [],
      "ReturnType": {
        "Name": "Double",
        "Namespace": "System",
        "GenericParameters": null,
        "IsArray": false,
        "IsReference": false
      }
    }
  ],
  "Traits": [],
  "SuperInterfaces": [],
  "ContractVersion": 65536,
  "GenericParameters": null,
  "Type": "Interface"
}