{
  "Name": "IBluetoothDevice",
  "Namespace": "Windows.Devices.Bluetooth",
  "Guid": "2335b15690d24a04aef50e20b9e6b707",
  "Methods": [
    {
      "Name": "get_DeviceId",
      "Parameters": [],
      "ReturnType": {
        "Name": "String",
        "Namespace": "System",
        "GenericParameters": null,
        "IsArray": false,
        "IsReference": false
      }
    },
    {
      "Name": "get_HostName",
      "Parameters": [],
      "ReturnType": {
        "Name": "HostName",
        "Namespace": "Windows.Networking",
        "GenericParameters": null,
        "IsArray": false,
        "IsReference": false
      }
    },
    {
      "Name": "get_Name",
      "Parameters": [],
      "ReturnType": {
        "Name": "String",
        "Namespace": "System",
        "GenericParameters": null,
        "IsArray": false,
        "IsReference": false
      }
    },
    {
      "Name": "get_ClassOfDevice",
      "Parameters": [],
      "ReturnType": {
        "Name": "BluetoothClassOfDevice",
        "Namespace": "Windows.Devices.Bluetooth",
        "GenericParameters": null,
        "IsArray": false,
        "IsReference": false
      }
    },
    {
      "Name": "get_SdpRecords",
      "Parameters": [],
      "ReturnType": {
        "Name": "IVectorView`1",
        "Namespace": "Windows.Foundation.Collections",
        "GenericParameters": [
          {
            "Name": "T",
            "Position": 0,
            "Type": {
              "Name": "IBuffer",
              "Namespace": "Windows.Storage.Streams",
              "GenericParameters": null,
              "IsArray": false,
              "IsReference": false
            }
          }
        ],
        "IsArray": false,
        "IsReference": false
      }
    },
    {
      "Name": "get_RfcommServices",
      "Parameters": [],
      "ReturnType": {
        "Name": "IVectorView`1",
        "Namespace": "Windows.Foundation.Collections",
        "GenericParameters": [
          {
            "Name": "T",
            "Position": 0,
            "Type": {
              "Name": "RfcommDeviceService",
              "Namespace": "Windows.Devices.Bluetooth.Rfcomm",
              "GenericParameters": null,
              "IsArray": false,
              "IsReference": false
            }
          }
        ],
        "IsArray": false,
        "IsReference": false
      }
    },
    {
      "Name": "get_ConnectionStatus",
      "Parameters": [],
      "ReturnType": {
        "Name": "BluetoothConnectionStatus",
        "Namespace": "Windows.Devices.Bluetooth",
        "GenericParameters": null,
        "IsArray": false,
        "IsReference": false
      }
    },
    {
      "Name": "get_BluetoothAddress",
      "Parameters": [],
      "ReturnType": {
        "Name": "UInt64",
        "Namespace": "System",
        "GenericParameters": null,
        "IsArray": false,
        "IsReference": false
      }
    },
    {
      "Name": "add_NameChanged",
      "Parameters": [
        {
          "Name": "handler",
          "Type": {
            "Name": "TypedEventHandler`2",
            "Namespace": "Windows.Foundation",
            "GenericParameters": [
              {
                "Name": "TSender",
                "Position": 0,
                "Type": {
                  "Name": "BluetoothDevice",
                  "Namespace": "Windows.Devices.Bluetooth",
                  "GenericParameters": null,
                  "IsArray": false,
                  "IsReference": false
                }
              },
              {
                "Name": "TResult",
                "Position": 1,
                "Type": {
                  "Name": "Object",
                  "Namespace": "System",
                  "GenericParameters": null,
                  "IsArray": false,
                  "IsReference": false
                }
              }
            ],
            "IsArray": false,
            "IsReference": false
          },
          "ParameterType": "In"
        }
      ],
      "ReturnType": {
        "Name": "EventRegistrationToken",
        "Namespace": "Windows.Foundation",
        "GenericParameters": null,
        "IsArray": false,
        "IsReference": false
      }
    },
    {
      "Name": "remove_NameChanged",
      "Parameters": [
        {
          "Name": "token",
          "Type": {
            "Name": "EventRegistrationToken",
            "Namespace": "Windows.Foundation",
            "GenericParameters": null,
            "IsArray": false,
            "IsReference": false
          },
          "ParameterType": "In"
        }
      ],
      "ReturnType": {
        "Name": "Void",
        "Namespace": "System",
        "GenericParameters": null,
        "IsArray": false,
        "IsReference": false
      }
    },
    {
      "Name": "add_SdpRecordsChanged",
      "Parameters": [
        {
          "Name": "handler",
          "Type": {
            "Name": "TypedEventHandler`2",
            "Namespace": "Windows.Foundation",
            "GenericParameters": [
              {
                "Name": "TSender",
                "Position": 0,
                "Type": {
                  "Name": "BluetoothDevice",
                  "Namespace": "Windows.Devices.Bluetooth",
                  "GenericParameters": null,
                  "IsArray": false,
                  "IsReference": false
                }
              },
              {
                "Name": "TResult",
                "Position": 1,
                "Type": {
                  "Name": "Object",
                  "Namespace": "System",
                  "GenericParameters": null,
                  "IsArray": false,
                  "IsReference": false
                }
              }
            ],
            "IsArray": false,
            "IsReference": false
          },
          "ParameterType": "In"
        }
      ],
      "ReturnType": {
        "Name": "EventRegistrationToken",
        "Namespace": "Windows.Foundation",
        "GenericParameters": null,
        "IsArray": false,
        "IsReference": false
      }
    },
    {
      "Name": "remove_SdpRecordsChanged",
      "Parameters": [
        {
          "Name": "token",
          "Type": {
            "Name": "EventRegistrationToken",
            "Namespace": "Windows.Foundation",
            "GenericParameters": null,
            "IsArray": false,
            "IsReference": false
          },
          "ParameterType": "In"
        }
      ],
      "ReturnType": {
        "Name": "Void",
        "Namespace": "System",
        "GenericParameters": null,
        "IsArray": false,
        "IsReference": false
      }
    },
    {
      "Name": "add_ConnectionStatusChanged",
      "Parameters": [
        {
          "Name": "handler",
          "Type": {
            "Name": "TypedEventHandler`2",
            "Namespace": "Windows.Foundation",
            "GenericParameters": [
              {
                "Name": "TSender",
                "Position": 0,
                "Type": {
                  "Name": "BluetoothDevice",
                  "Namespace": "Windows.Devices.Bluetooth",
                  "GenericParameters": null,
                  "IsArray": false,
                  "IsReference": false
                }
              },
              {
                "Name": "TResult",
                "Position": 1,
                "Type": {
                  "Name": "Object",
                  "Namespace": "System",
                  "GenericParameters": null,
                  "IsArray": false,
                  "IsReference": false
                }
              }
            ],
            "IsArray": false,
            "IsReference": false
          },
          "ParameterType": "In"
        }
      ],
      "ReturnType": {
        "Name": "EventRegistrationToken",
        "Namespace": "Windows.Foundation",
        "GenericParameters": null,
        "IsArray": false,
        "IsReference": false
      }
    },
    {
      "Name": "remove_ConnectionStatusChanged",
      "Parameters": [
        {
          "Name": "token",
          "Type": {
            "Name": "EventRegistrationToken",
            "Namespace": "Windows.Foundation",
            "GenericParameters": null,
            "IsArray": false,
            "IsReference": false
          },
          "ParameterType": "In"
        }
      ],
      "ReturnType": {
        "Name": "Void",
        "Namespace": "System",
        "GenericParameters": null,
        "IsArray": false,
        "IsReference": false
      }
    }
  ],
  "Traits": [],
  "SuperInterfaces": [],
  "GenericParameters": null,
  "Type": "Interface"
}