{
  "Name": "LightSensor",
  "Namespace": "Windows.Devices.Sensors",
  "Interfaces": [
    {
      "Name": "ILightSensor",
      "Namespace": "Windows.Devices.Sensors",
      "GenericParameters": null,
      "IsArray": false,
      "IsReference": false
    },
    {
      "Name": "ILightSensorDeviceId",
      "Namespace": "Windows.Devices.Sensors",
      "GenericParameters": null,
      "IsArray": false,
      "IsReference": false
    },
    {
      "Name": "ILightSensor2",
      "Namespace": "Windows.Devices.Sensors",
      "GenericParameters": null,
      "IsArray": false,
      "IsReference": false
    },
    {
      "Name": "ILightSensor3",
      "Namespace": "Windows.Devices.Sensors",
      "GenericParameters": null,
      "IsArray": false,
      "IsReference": false
    }
  ],
  "Traits": [
    {
      "Interfaces": [
        {
          "Name": "ILightSensorStatics",
          "Namespace": "Windows.Devices.Sensors"
        },
        {
          "Name": "ILightSensorStatics2",
          "Namespace": "Windows.Devices.Sensors"
        }
      ],
      "TraitType": "Static"
    },
    {
      "DefaultInterface": {
        "Name": "ILightSensor",
        "Namespace": "Windows.Devices.Sensors",
        "GenericParameters": null,
        "IsArray": false,
        "IsReference": false
      },
      "TraitType": "DefaultInterface"
    }
  ],
  "Type": "Class"
}