{
  "Name": "MenuBar",
  "Namespace": "Windows.UI.Xaml.Controls",
  "Interfaces": [
    {
      "Name": "IMenuBar",
      "Namespace": "Windows.UI.Xaml.Controls",
      "GenericParameters": null,
      "IsArray": false,
      "IsReference": false
    }
  ],
  "Traits": [
    {
      "Interfaces": [
        {
          "Name": "IMenuBarStatics",
          "Namespace": "Windows.UI.Xaml.Controls"
        }
      ],
      "TraitType": "Static"
    },
    {
      "DefaultInterface": {
        "Name": "IMenuBar",
        "Namespace": "Windows.UI.Xaml.Controls",
        "GenericParameters": null,
        "IsArray": false,
        "IsReference": false
      },
      "TraitType": "DefaultInterface"
    },
    {
      "CompositionFactoryTypes": [
        {
          "Name": "IMenuBarFactory",
          "Namespace": "Windows.UI.Xaml.Controls",
          "GenericParameters": null,
          "IsArray": false,
          "IsReference": false
        }
      ],
      "TraitType": "CompositionActivation"
    },
    {
      "Superclass": {
        "Name": "Control",
        "Namespace": "Windows.UI.Xaml.Controls",
        "GenericParameters": null,
        "IsArray": false,
        "IsReference": false
      },
      "TraitType": "Superclass"
    }
  ],
  "Type": "Class"
}