{
  "Name": "ICoreImmersiveApplication2",
  "Namespace": "Windows.ApplicationModel.Core",
  "Guid": "828e1e36e9e34cfc9b6648b78ea9bb2c",
  "Methods": [
    {
      "Name": "CreateNewView",
      "Parameters": [],
      "ReturnType": {
        "Name": "CoreApplicationView",
        "Namespace": "Windows.ApplicationModel.Core",
        "GenericParameters": null,
        "IsArray": false,
        "IsReference": false
      }
    }
  ],
  "Traits": [],
  "SuperInterfaces": [],
  "GenericParameters": null,
  "Type": "Interface"
}