{
  "Name": "IShareWindowCommandSource",
  "Namespace": "Windows.UI.Shell",
  "Guid": "cb3b7ae36b9c561ebccc61e68e0abfef",
  "Methods": [
    {
      "Name": "Start",
      "Parameters": [],
      "ReturnType": {
        "Name": "Void",
        "Namespace": "System",
        "GenericParameters": null,
        "IsArray": false,
        "IsReference": false
      }
    },
    {
      "Name": "Stop",
      "Parameters": [],
      "ReturnType": {
        "Name": "Void",
        "Namespace": "System",
        "GenericParameters": null,
        "IsArray": false,
        "IsReference": false
      }
    },
    {
      "Name": "ReportCommandChanged",
      "Parameters": [],
      "ReturnType": {
        "Name": "Void",
        "Namespace": "System",
        "GenericParameters": null,
        "IsArray": false,
        "IsReference": false
      }
    },
    {
      "Name": "add_CommandRequested",
      "Parameters": [
        {
          "Name": "handler",
          "Type": {
            "Name": "TypedEventHandler`2",
            "Namespace": "Windows.Foundation",
            "GenericParameters": [
              {
                "Name": "TSender",
                "Position": 0,
                "Type": {
                  "Name": "ShareWindowCommandSource",
                  "Namespace": "Windows.UI.Shell",
                  "GenericParameters": null,
                  "IsArray": false,
                  "IsReference": false
                }
              },
              {
                "Name": "TResult",
                "Position": 1,
                "Type": {
                  "Name": "ShareWindowCommandEventArgs",
                  "Namespace": "Windows.UI.Shell",
                  "GenericParameters": null,
                  "IsArray": false,
                  "IsReference": false
                }
              }
            ],
            "IsArray": false,
            "IsReference": false
          },
          "ParameterType": "In"
        }
      ],
      "ReturnType": {
        "Name": "EventRegistrationToken",
        "Namespace": "Windows.Foundation",
        "GenericParameters": null,
        "IsArray": false,
        "IsReference": false
      }
    },
    {
      "Name": "remove_CommandRequested",
      "Parameters": [
        {
          "Name": "token",
          "Type": {
            "Name": "EventRegistrationToken",
            "Namespace": "Windows.Foundation",
            "GenericParameters": null,
            "IsArray": false,
            "IsReference": false
          },
          "ParameterType": "In"
        }
      ],
      "ReturnType": {
        "Name": "Void",
        "Namespace": "System",
        "GenericParameters": null,
        "IsArray": false,
        "IsReference": false
      }
    },
    {
      "Name": "add_CommandInvoked",
      "Parameters": [
        {
          "Name": "handler",
          "Type": {
            "Name": "TypedEventHandler`2",
            "Namespace": "Windows.Foundation",
            "GenericParameters": [
              {
                "Name": "TSender",
                "Position": 0,
                "Type": {
                  "Name": "ShareWindowCommandSource",
                  "Namespace": "Windows.UI.Shell",
                  "GenericParameters": null,
                  "IsArray": false,
                  "IsReference": false
                }
              },
              {
                "Name": "TResult",
                "Position": 1,
                "Type": {
                  "Name": "ShareWindowCommandEventArgs",
                  "Namespace": "Windows.UI.Shell",
                  "GenericParameters": null,
                  "IsArray": false,
                  "IsReference": false
                }
              }
            ],
            "IsArray": false,
            "IsReference": false
          },
          "ParameterType": "In"
        }
      ],
      "ReturnType": {
        "Name": "EventRegistrationToken",
        "Namespace": "Windows.Foundation",
        "GenericParameters": null,
        "IsArray": false,
        "IsReference": false
      }
    },
    {
      "Name": "remove_CommandInvoked",
      "Parameters": [
        {
          "Name": "token",
          "Type": {
            "Name": "EventRegistrationToken",
            "Namespace": "Windows.Foundation",
            "GenericParameters": null,
            "IsArray": false,
            "IsReference": false
          },
          "ParameterType": "In"
        }
      ],
      "ReturnType": {
        "Name": "Void",
        "Namespace": "System",
        "GenericParameters": null,
        "IsArray": false,
        "IsReference": false
      }
    }
  ],
  "Traits": [],
  "SuperInterfaces": [],
  "GenericParameters": null,
  "Type": "Interface"
}