{
  "Name": "IGetActivationFactory",
  "Namespace": "Windows.Foundation",
  "Guid": "4edb8ee296dd49a794f74607ddab8e3c",
  "Methods": [
    {
      "Name": "GetActivationFactory",
      "Parameters": [
        {
          "Name": "activatableClassId",
          "Type": {
            "Name": "String",
            "Namespace": "System",
            "GenericParameters": null,
            "IsArray": false,
            "IsReference": false
          },
          "ParameterType": "In"
        }
      ],
      "ReturnType": {
        "Name": "Object",
        "Namespace": "System",
        "GenericParameters": null,
        "IsArray": false,
        "IsReference": false
      }
    }
  ],
  "Traits": [],
  "SuperInterfaces": [],
  "ContractVersion": 65536,
  "GenericParameters": null,
  "Type": "Interface"
}