{
  "Name": "ILoggingChannelFactory2",
  "Namespace": "Windows.Foundation.Diagnostics",
  "Guid": "4c6ef5dd3b274dc999f0299c6e4603a1",
  "Methods": [
    {
      "Name": "CreateWithOptions",
      "Parameters": [
        {
          "Name": "name",
          "Type": {
            "Name": "String",
            "Namespace": "System",
            "GenericParameters": null,
            "IsArray": false,
            "IsReference": false
          },
          "ParameterType": "In"
        },
        {
          "Name": "options",
          "Type": {
            "Name": "LoggingChannelOptions",
            "Namespace": "Windows.Foundation.Diagnostics",
            "GenericParameters": null,
            "IsArray": false,
            "IsReference": false
          },
          "ParameterType": "In"
        }
      ],
      "ReturnType": {
        "Name": "LoggingChannel",
        "Namespace": "Windows.Foundation.Diagnostics",
        "GenericParameters": null,
        "IsArray": false,
        "IsReference": false
      }
    },
    {
      "Name": "CreateWithOptionsAndId",
      "Parameters": [
        {
          "Name": "name",
          "Type": {
            "Name": "String",
            "Namespace": "System",
            "GenericParameters": null,
            "IsArray": false,
            "IsReference": false
          },
          "ParameterType": "In"
        },
        {
          "Name": "options",
          "Type": {
            "Name": "LoggingChannelOptions",
            "Namespace": "Windows.Foundation.Diagnostics",
            "GenericParameters": null,
            "IsArray": false,
            "IsReference": false
          },
          "ParameterType": "In"
        },
        {
          "Name": "id",
          "Type": {
            "Name": "Guid",
            "Namespace": "System",
            "GenericParameters": null,
            "IsArray": false,
            "IsReference": false
          },
          "ParameterType": "In"
        }
      ],
      "ReturnType": {
        "Name": "LoggingChannel",
        "Namespace": "Windows.Foundation.Diagnostics",
        "GenericParameters": null,
        "IsArray": false,
        "IsReference": false
      }
    }
  ],
  "Traits": [],
  "SuperInterfaces": [],
  "ContractVersion": 65536,
  "GenericParameters": null,
  "Type": "Interface"
}