{
  "Name": "ISpreadsheetItemProvider",
  "Namespace": "Windows.UI.Xaml.Automation.Provider",
  "Guid": "ebde8f9260154826b71947521a81c67e",
  "Methods": [
    {
      "Name": "get_Formula",
      "Parameters": [],
      "ReturnType": {
        "Name": "String",
        "Namespace": "System",
        "GenericParameters": null,
        "IsArray": false,
        "IsReference": false
      }
    },
    {
      "Name": "GetAnnotationObjects",
      "Parameters": [],
      "ReturnType": {
        "Name": "IRawElementProviderSimple",
        "Namespace": "Windows.UI.Xaml.Automation.Provider",
        "GenericParameters": null,
        "IsArray": true,
        "IsReference": false
      }
    },
    {
      "Name": "GetAnnotationTypes",
      "Parameters": [],
      "ReturnType": {
        "Name": "AnnotationType",
        "Namespace": "Windows.UI.Xaml.Automation",
        "GenericParameters": null,
        "IsArray": true,
        "IsReference": false
      }
    }
  ],
  "Traits": [],
  "SuperInterfaces": [],
  "ContractVersion": 65536,
  "GenericParameters": null,
  "Type": "Interface"
}