{
  "Name": "IStoreProductResult",
  "Namespace": "Windows.Services.Store",
  "Guid": "b7674f733c874ee18201f428359bd3af",
  "Methods": [
    {
      "Name": "get_Product",
      "Parameters": [],
      "ReturnType": {
        "Name": "StoreProduct",
        "Namespace": "Windows.Services.Store",
        "GenericParameters": null,
        "IsArray": false,
        "IsReference": false
      }
    },
    {
      "Name": "get_ExtendedError",
      "Parameters": [],
      "ReturnType": {
        "Name": "HResult",
        "Namespace": "Windows.Foundation",
        "GenericParameters": null,
        "IsArray": false,
        "IsReference": false
      }
    }
  ],
  "Traits": [],
  "SuperInterfaces": [],
  "ContractVersion": 65536,
  "GenericParameters": null,
  "Type": "Interface"
}