{
  "Name": "ILoggingActivity2",
  "Namespace": "Windows.Foundation.Diagnostics",
  "Guid": "26c298086322456aaf8280c8642f178b",
  "Methods": [
    {
      "Name": "get_Channel",
      "Parameters": [],
      "ReturnType": {
        "Name": "LoggingChannel",
        "Namespace": "Windows.Foundation.Diagnostics",
        "GenericParameters": null,
        "IsArray": false,
        "IsReference": false
      }
    },
    {
      "Name": "StopActivity",
      "Parameters": [
        {
          "Name": "stopEventName",
          "Type": {
            "Name": "String",
            "Namespace": "System",
            "GenericParameters": null,
            "IsArray": false,
            "IsReference": false
          },
          "ParameterType": "In"
        }
      ],
      "ReturnType": {
        "Name": "Void",
        "Namespace": "System",
        "GenericParameters": null,
        "IsArray": false,
        "IsReference": false
      }
    },
    {
      "Name": "StopActivity",
      "Parameters": [
        {
          "Name": "stopEventName",
          "Type": {
            "Name": "String",
            "Namespace": "System",
            "GenericParameters": null,
            "IsArray": false,
            "IsReference": false
          },
          "ParameterType": "In"
        },
        {
          "Name": "fields",
          "Type": {
            "Name": "LoggingFields",
            "Namespace": "Windows.Foundation.Diagnostics",
            "GenericParameters": null,
            "IsArray": false,
            "IsReference": false
          },
          "ParameterType": "In"
        }
      ],
      "ReturnType": {
        "Name": "Void",
        "Namespace": "System",
        "GenericParameters": null,
        "IsArray": false,
        "IsReference": false
      }
    },
    {
      "Name": "StopActivity",
      "Parameters": [
        {
          "Name": "stopEventName",
          "Type": {
            "Name": "String",
            "Namespace": "System",
            "GenericParameters": null,
            "IsArray": false,
            "IsReference": false
          },
          "ParameterType": "In"
        },
        {
          "Name": "fields",
          "Type": {
            "Name": "LoggingFields",
            "Namespace": "Windows.Foundation.Diagnostics",
            "GenericParameters": null,
            "IsArray": false,
            "IsReference": false
          },
          "ParameterType": "In"
        },
        {
          "Name": "options",
          "Type": {
            "Name": "LoggingOptions",
            "Namespace": "Windows.Foundation.Diagnostics",
            "GenericParameters": null,
            "IsArray": false,
            "IsReference": false
          },
          "ParameterType": "In"
        }
      ],
      "ReturnType": {
        "Name": "Void",
        "Namespace": "System",
        "GenericParameters": null,
        "IsArray": false,
        "IsReference": false
      }
    }
  ],
  "Traits": [],
  "SuperInterfaces": [
    {
      "Name": "ILoggingActivity",
      "Namespace": "Windows.Foundation.Diagnostics",
      "GenericParameters": null,
      "IsArray": false,
      "IsReference": false
    },
    {
      "Name": "IClosable",
      "Namespace": "Windows.Foundation",
      "GenericParameters": null,
      "IsArray": false,
      "IsReference": false
    },
    {
      "Name": "ILoggingTarget",
      "Namespace": "Windows.Foundation.Diagnostics",
      "GenericParameters": null,
      "IsArray": false,
      "IsReference": false
    }
  ],
  "ContractVersion": 65536,
  "GenericParameters": null,
  "Type": "Interface"
}