{
  "Name": "IUriRuntimeClass",
  "Namespace": "Windows.Foundation",
  "Guid": "9e365e5748b24160956fc7385120bbfc",
  "Methods": [
    {
      "Name": "get_AbsoluteUri",
      "Parameters": [],
      "ReturnType": {
        "Name": "String",
        "Namespace": "System",
        "GenericParameters": null,
        "IsArray": false,
        "IsReference": false
      }
    },
    {
      "Name": "get_DisplayUri",
      "Parameters": [],
      "ReturnType": {
        "Name": "String",
        "Namespace": "System",
        "GenericParameters": null,
        "IsArray": false,
        "IsReference": false
      }
    },
    {
      "Name": "get_Domain",
      "Parameters": [],
      "ReturnType": {
        "Name": "String",
        "Namespace": "System",
        "GenericParameters": null,
        "IsArray": false,
        "IsReference": false
      }
    },
    {
      "Name": "get_Extension",
      "Parameters": [],
      "ReturnType": {
        "Name": "String",
        "Namespace": "System",
        "GenericParameters": null,
        "IsArray": false,
        "IsReference": false
      }
    },
    {
      "Name": "get_Fragment",
      "Parameters": [],
      "ReturnType": {
        "Name": "String",
        "Namespace": "System",
        "GenericParameters": null,
        "IsArray": false,
        "IsReference": false
      }
    },
    {
      "Name": "get_Host",
      "Parameters": [],
      "ReturnType": {
        "Name": "String",
        "Namespace": "System",
        "GenericParameters": null,
        "IsArray": false,
        "IsReference": false
      }
    },
    {
      "Name": "get_Password",
      "Parameters": [],
      "ReturnType": {
        "Name": "String",
        "Namespace": "System",
        "GenericParameters": null,
        "IsArray": false,
        "IsReference": false
      }
    },
    {
      "Name": "get_Path",
      "Parameters": [],
      "ReturnType": {
        "Name": "String",
        "Namespace": "System",
        "GenericParameters": null,
        "IsArray": false,
        "IsReference": false
      }
    },
    {
      "Name": "get_Query",
      "Parameters": [],
      "ReturnType": {
        "Name": "String",
        "Namespace": "System",
        "GenericParameters": null,
        "IsArray": false,
        "IsReference": false
      }
    },
    {
      "Name": "get_QueryParsed",
      "Parameters": [],
      "ReturnType": {
        "Name": "WwwFormUrlDecoder",
        "Namespace": "Windows.Foundation",
        "GenericParameters": null,
        "IsArray": false,
        "IsReference": false
      }
    },
    {
      "Name": "get_RawUri",
      "Parameters": [],
      "ReturnType": {
        "Name": "String",
        "Namespace": "System",
        "GenericParameters": null,
        "IsArray": false,
        "IsReference": false
      }
    },
    {
      "Name": "get_SchemeName",
      "Parameters": [],
      "ReturnType": {
        "Name": "String",
        "Namespace": "System",
        "GenericParameters": null,
        "IsArray": false,
        "IsReference": false
      }
    },
    {
      "Name": "get_UserName",
      "Parameters": [],
      "ReturnType": {
        "Name": "String",
        "Namespace": "System",
        "GenericParameters": null,
        "IsArray": false,
        "IsReference": false
      }
    },
    {
      "Name": "get_Port",
      "Parameters": [],
      "ReturnType": {
        "Name": "Int32",
        "Namespace": "System",
        "GenericParameters": null,
        "IsArray": false,
        "IsReference": false
      }
    },
    {
      "Name": "get_Suspicious",
      "Parameters": [],
      "ReturnType": {
        "Name": "Boolean",
        "Namespace": "System",
        "GenericParameters": null,
        "IsArray": false,
        "IsReference": false
      }
    },
    {
      "Name": "Equals",
      "Parameters": [
        {
          "Name": "pUri",
          "Type": {
            "Name": "Uri",
            "Namespace": "Windows.Foundation",
            "GenericParameters": null,
            "IsArray": false,
            "IsReference": false
          },
          "ParameterType": "In"
        }
      ],
      "ReturnType": {
        "Name": "Boolean",
        "Namespace": "System",
        "GenericParameters": null,
        "IsArray": false,
        "IsReference": false
      }
    },
    {
      "Name": "CombineUri",
      "Parameters": [
        {
          "Name": "relativeUri",
          "Type": {
            "Name": "String",
            "Namespace": "System",
            "GenericParameters": null,
            "IsArray": false,
            "IsReference": false
          },
          "ParameterType": "In"
        }
      ],
      "ReturnType": {
        "Name": "Uri",
        "Namespace": "Windows.Foundation",
        "GenericParameters": null,
        "IsArray": false,
        "IsReference": false
      }
    }
  ],
  "Traits": [],
  "SuperInterfaces": [],
  "GenericParameters": null,
  "Type": "Interface"
}