{
  "Name": "ITableItemPatternIdentifiersStatics",
  "Namespace": "Microsoft.UI.Xaml.Automation",
  "Guid": "81d24bd766fb53ef9b32d00f9c240a14",
  "Methods": [
    {
      "Name": "get_ColumnHeaderItemsProperty",
      "Parameters": [],
      "ReturnType": {
        "Name": "AutomationProperty",
        "Namespace": "Microsoft.UI.Xaml.Automation",
        "GenericParameters": null,
        "IsArray": false,
        "IsReference": false
      }
    },
    {
      "Name": "get_RowHeaderItemsProperty",
      "Parameters": [],
      "ReturnType": {
        "Name": "AutomationProperty",
        "Namespace": "Microsoft.UI.Xaml.Automation",
        "GenericParameters": null,
        "IsArray": false,
        "IsReference": false
      }
    }
  ],
  "Traits": [],
  "SuperInterfaces": [],
  "ContractVersion": 65536,
  "GenericParameters": null,
  "Type": "Interface"
}