{
  "Name": "IDragPatternIdentifiersStatics",
  "Namespace": "Microsoft.UI.Xaml.Automation",
  "Guid": "482eee700bfc55529e7d8dffc526b2f7",
  "Methods": [
    {
      "Name": "get_DropEffectProperty",
      "Parameters": [],
      "ReturnType": {
        "Name": "AutomationProperty",
        "Namespace": "Microsoft.UI.Xaml.Automation",
        "GenericParameters": null,
        "IsArray": false,
        "IsReference": false
      }
    },
    {
      "Name": "get_DropEffectsProperty",
      "Parameters": [],
      "ReturnType": {
        "Name": "AutomationProperty",
        "Namespace": "Microsoft.UI.Xaml.Automation",
        "GenericParameters": null,
        "IsArray": false,
        "IsReference": false
      }
    },
    {
      "Name": "get_GrabbedItemsProperty",
      "Parameters": [],
      "ReturnType": {
        "Name": "AutomationProperty",
        "Namespace": "Microsoft.UI.Xaml.Automation",
        "GenericParameters": null,
        "IsArray": false,
        "IsReference": false
      }
    },
    {
      "Name": "get_IsGrabbedProperty",
      "Parameters": [],
      "ReturnType": {
        "Name": "AutomationProperty",
        "Namespace": "Microsoft.UI.Xaml.Automation",
        "GenericParameters": null,
        "IsArray": false,
        "IsReference": false
      }
    }
  ],
  "Traits": [],
  "SuperInterfaces": [],
  "ContractVersion": 65536,
  "GenericParameters": null,
  "Type": "Interface"
}