{
  "Name": "IconSource",
  "Namespace": "Microsoft.UI.Xaml.Controls",
  "Interfaces": [
    {
      "Name": "IIconSource",
      "Namespace": "Microsoft.UI.Xaml.Controls",
      "GenericParameters": null,
      "IsArray": false,
      "IsReference": false
    },
    {
      "Name": "IIconSourceOverrides",
      "Namespace": "Microsoft.UI.Xaml.Controls",
      "GenericParameters": null,
      "IsArray": false,
      "IsReference": false
    }
  ],
  "Traits": [
    {
      "Interfaces": [
        {
          "Name": "IIconSourceStatics",
          "Namespace": "Microsoft.UI.Xaml.Controls"
        }
      ],
      "TraitType": "Static"
    },
    {
      "DefaultInterface": {
        "Name": "IIconSource",
        "Namespace": "Microsoft.UI.Xaml.Controls",
        "GenericParameters": null,
        "IsArray": false,
        "IsReference": false
      },
      "TraitType": "DefaultInterface"
    },
    {
      "Superclass": {
        "Name": "DependencyObject",
        "Namespace": "Microsoft.UI.Xaml",
        "GenericParameters": null,
        "IsArray": false,
        "IsReference": false
      },
      "TraitType": "Superclass"
    },
    {
      "TraitType": "Subclass"
    }
  ],
  "Type": "Class"
}