{
  "Name": "NavigationView",
  "Namespace": "Microsoft.UI.Xaml.Controls",
  "Interfaces": [
    {
      "Name": "INavigationView",
      "Namespace": "Microsoft.UI.Xaml.Controls",
      "GenericParameters": null,
      "IsArray": false,
      "IsReference": false
    },
    {
      "Name": "INavigationView2",
      "Namespace": "Microsoft.UI.Xaml.Controls",
      "GenericParameters": null,
      "IsArray": false,
      "IsReference": false
    }
  ],
  "Traits": [
    {
      "Interfaces": [
        {
          "Name": "INavigationViewStatics2",
          "Namespace": "Microsoft.UI.Xaml.Controls"
        },
        {
          "Name": "INavigationViewStatics",
          "Namespace": "Microsoft.UI.Xaml.Controls"
        }
      ],
      "TraitType": "Static"
    },
    {
      "DefaultInterface": {
        "Name": "INavigationView",
        "Namespace": "Microsoft.UI.Xaml.Controls",
        "GenericParameters": null,
        "IsArray": false,
        "IsReference": false
      },
      "TraitType": "DefaultInterface"
    },
    {
      "CompositionFactoryTypes": [
        {
          "Name": "INavigationViewFactory",
          "Namespace": "Microsoft.UI.Xaml.Controls",
          "GenericParameters": null,
          "IsArray": false,
          "IsReference": false
        }
      ],
      "TraitType": "CompositionActivation"
    },
    {
      "Superclass": {
        "Name": "ContentControl",
        "Namespace": "Microsoft.UI.Xaml.Controls",
        "GenericParameters": null,
        "IsArray": false,
        "IsReference": false
      },
      "TraitType": "Superclass"
    }
  ],
  "Type": "Class"
}