{
  "Name": "IRatingItemImageInfoFactory",
  "Namespace": "Microsoft.UI.Xaml.Controls",
  "Guid": "4acc8cacbca8538095e4345c1be256b2",
  "Methods": [
    {
      "Name": "CreateInstance",
      "Parameters": [
        {
          "Name": "baseInterface",
          "Type": {
            "Name": "Object",
            "Namespace": "System",
            "GenericParameters": null,
            "IsArray": false,
            "IsReference": false
          },
          "ParameterType": "In"
        },
        {
          "Name": "innerInterface",
          "Type": {
            "Name": "Object",
            "Namespace": "System",
            "GenericParameters": null,
            "IsArray": false,
            "IsReference": true
          },
          "ParameterType": "Out"
        }
      ],
      "ReturnType": {
        "Name": "RatingItemImageInfo",
        "Namespace": "Microsoft.UI.Xaml.Controls",
        "GenericParameters": null,
        "IsArray": false,
        "IsReference": false
      }
    }
  ],
  "Traits": [],
  "SuperInterfaces": [],
  "GenericParameters": null,
  "Type": "Interface"
}