{
  "Name": "IAppWindowTitleBarStatics",
  "Namespace": "Microsoft.UI.Windowing",
  "Guid": "9e1da52e8b1554d6a886f7b9f9d930b2",
  "Methods": [
    {
      "Name": "IsCustomizationSupported",
      "Parameters": [],
      "ReturnType": {
        "Name": "Boolean",
        "Namespace": "System",
        "GenericParameters": null,
        "IsArray": false,
        "IsReference": false
      }
    }
  ],
  "Traits": [],
  "SuperInterfaces": [],
  "ContractVersion": 65536,
  "GenericParameters": null,
  "Type": "Interface"
}