{
  "Name": "CompositionEasingFunction",
  "Namespace": "Microsoft.UI.Composition",
  "Interfaces": [
    {
      "Name": "ICompositionEasingFunction",
      "Namespace": "Microsoft.UI.Composition",
      "GenericParameters": null,
      "IsArray": false,
      "IsReference": false
    }
  ],
  "Traits": [
    {
      "Interfaces": [
        {
          "Name": "ICompositionEasingFunctionStatics",
          "Namespace": "Microsoft.UI.Composition"
        }
      ],
      "TraitType": "Static"
    },
    {
      "DefaultInterface": {
        "Name": "ICompositionEasingFunction",
        "Namespace": "Microsoft.UI.Composition",
        "GenericParameters": null,
        "IsArray": false,
        "IsReference": false
      },
      "TraitType": "DefaultInterface"
    },
    {
      "Superclass": {
        "Name": "CompositionObject",
        "Namespace": "Microsoft.UI.Composition",
        "GenericParameters": null,
        "IsArray": false,
        "IsReference": false
      },
      "TraitType": "Superclass"
    },
    {
      "TraitType": "Subclass"
    }
  ],
  "Type": "Class"
}